fastq_validation-1.0.5.dist-info/METADATA
fastq_validation-1.0.5.dist-info/WHEEL
fastq_validation-1.0.5.dist-info/licenses/LICENSE
fastq_validation/__init__.py
fastq_validation/fastq_validation.cpython-39-s390x-linux-gnu.so
fastq_validation-1.0.5.dist-info/RECORD
