Metadata-Version: 2.4
Name: fastq_validation
Version: 1.0.5
Classifier: Development Status :: 2 - Pre-Alpha
Classifier: Programming Language :: Rust
Classifier: Programming Language :: Python :: Implementation :: CPython
Classifier: Programming Language :: Python :: Implementation :: PyPy
License-File: LICENSE
Summary: Simple and fast validation of FASTQ files. Checks if given files are illumina/ONT
Author-email: Jeremy Westhead <jeremy.westhead@ndm.ox.ac.uk>
Requires-Python: >=3.8, <3.13
Project-URL: Source, https://github.com/GlobalPathogenAnalysisService/fastq_validation
